mini_logger/__init__.py
mini_logger/mini_logger.py
py_mini_logger-0.1.6.dist-info/LICENSE
py_mini_logger-0.1.6.dist-info/METADATA
py_mini_logger-0.1.6.dist-info/WHEEL
py_mini_logger-0.1.6.dist-info/RECORD
