Metadata-Version: 2.3
Name: py_mini_logger
Version: 0.1.6
Summary: Easily run bash commands with boolean conversion utilities
License: apache
Author: lamnguyenx
Author-email: lamfm95@gmail.com
Requires-Python: >=3.7,<4.0
Classifier: License :: Other/Proprietary License
Classifier: Programming Language :: Python :: 3
Classifier: Programming Language :: Python :: 3.7
Classifier: Programming Language :: Python :: 3.8
Classifier: Programming Language :: Python :: 3.9
Classifier: Programming Language :: Python :: 3.10
Classifier: Programming Language :: Python :: 3.11
Classifier: Programming Language :: Python :: 3.12
Classifier: Programming Language :: Python :: 3.13
Provides-Extra: booleanify
Project-URL: Homepage, https://github.com/lamnguyenx/mini_logger.git
